riopg/__init__.py
riopg/connection.py
riopg/cursor.py
riopg/pool.py
riopg-0.1.1.dist-info/DESCRIPTION.rst
riopg-0.1.1.dist-info/METADATA
riopg-0.1.1.dist-info/RECORD
riopg-0.1.1.dist-info/WHEEL
riopg-0.1.1.dist-info/metadata.json
riopg-0.1.1.dist-info/top_level.txt
