Metadata-Version: 2.0
Name: riopg
Version: 0.1.1
Summary: A postgresql library for (cu|t)rio
Home-page: https://github.com/Fuyukai/riopg
Author: Laura Dickinson
Author-email: l@veriny.tf
License: LGPLv3
Platform: UNKNOWN
Requires-Python: >=3.6.0
Requires-Dist: multio (<0.4.0,>=0.2.0)
Requires-Dist: psycopg2 (<2.8,>=2.7)
Provides-Extra: tests
Requires-Dist: pytest; extra == 'tests'
Requires-Dist: pytest-cov; extra == 'tests'
Requires-Dist: codecov; extra == 'tests'
Requires-Dist: trio (>=0.5.0); extra == 'tests'
Requires-Dist: curio (>=0.8); extra == 'tests'
